[
  {
    "id": "832f886a-04a8-49c0-9730-4476d1810695",
    "image": "1747685172782-629696685.jpg",
    "imageTitle": "ThinkSpire 12 Session 2 – Empowering Future Leaders at the University of Scholars",
    "categoryName": "Seminar"
  },
  {
    "id": "80d23e50-bdcd-4ab0-a287-b682ec9a72df",
    "image": "1747685185221-380267890.jpg",
    "imageTitle": "University of Scholars Inter Department Cricket Battle 2025",
    "categoryName": "Sports"
  },
  {
    "id": "18bc64f7-04b1-4e36-b4d3-3c45eb087528",
    "image": "1747685206636-277050758.jpg",
    "imageTitle": "University of Scholars Celebrates Its 1st Convocation Ceremony",
    "categoryName": "Convocation"
  },
  {
    "id": "8eed8b36-b30e-49fb-9264-f821b86af1f1",
    "image": "1747685219242-526823962.jpg",
    "imageTitle": "Rangpur Riders vs Bowler Hunters – Clash of Titans in the 2025 Global Super League",
    "categoryName": "Sports"
  },
  {
    "id": "d044e819-fb1d-4bd9-b5cc-3f5c997d42df",
    "image": "1747685416058-463812550.jpg",
    "imageTitle": "Winter Pitha and Puli Festival",
    "categoryName": "Festival"
  },
  {
    "id": "e8ee2333-8823-49d2-b65c-d29e9a90161f",
    "image": "1747769819499-183399881.jpg",
    "imageTitle": "CSE Intra Department Cricket Tournament 2024 – Fostering Team Spirit and Sportsmanship",
    "categoryName": "Sports"
  },
  {
    "id": "cd270281-cd07-485a-8c8f-e428381d9556",
    "image": "1747769996939-455834402.jpeg",
    "imageTitle": "Fashion Design Exhibition Presented by the Textile Department",
    "categoryName": "Function"
  },
  {
    "id": "e61c0b38-3f01-407e-9a8c-390db45b91aa",
    "image": "1747824127306-168625389.jpg",
    "imageTitle": "A New Chapter Begins: Celebrating the Convocation of CSE Graduates at University of Scholars",
    "categoryName": "Convocation"
  },
  {
    "id": "ed8aeb97-5a30-4421-886b-157e2c821ee5",
    "image": "1747824254544-753960689.jpg",
    "imageTitle": "Honoring Success: CSE Graduates of University of Scholars Receive Certificates from Vice Chancellor Prof. Dr. Enamul Basher",
    "categoryName": "Convocation"
  },
  {
    "id": "5bb8cba4-c698-4b75-99eb-0e4fde3256fb",
    "image": "1747832235897-163169227.jpg",
    "imageTitle": "University of Scholars presents: 3rd Intra University Programming Contest",
    "categoryName": "Programming Contest"
  },
  {
    "id": "0c5df214-c92c-48b8-aa7e-15457e3b20cf",
    "image": "1747832481638-20190884.jpg",
    "imageTitle": "Beyond Boundaries 24",
    "categoryName": "Programming Contest"
  },
  {
    "id": "30a64a86-51a0-49d2-a500-9ad213ecb38c",
    "image": "1747832774150-558474948.jpg",
    "imageTitle": "Scholars Football Tournament 2025",
    "categoryName": "Sports"
  },
  {
    "id": "b77b24a1-8cd0-4334-8ae7-ed7269f6da81",
    "image": "1747833686901-2520025.jpg",
    "imageTitle": "Clemon Indoor Cricket Tournament 2023",
    "categoryName": "Sports"
  },
  {
    "id": "d360587e-9cfb-408c-9f08-99f2bf665edd",
    "image": "1747833826136-398633551.jpg",
    "imageTitle": "পিঠা উৎসব ১৪৩০",
    "categoryName": "Festival"
  },
  {
    "id": "a794cf11-45d8-4a83-80de-7ba61086c05c",
    "image": "1747834151303-865599444.jpg",
    "imageTitle": "Digital Marketing from Beginners to Advanced",
    "categoryName": "Seminar"
  },
  {
    "id": "0ee04088-f7a2-4e2c-bbc5-d78a91d75fb7",
    "image": "1747834914312-948713168.jpg",
    "imageTitle": "Excel With Data Analytics",
    "categoryName": "Seminar"
  },
  {
    "id": "8111b9ad-87a4-47f0-a5ea-e2fb5a6ec6f4",
    "image": "1747835532335-532957371.jpg",
    "imageTitle": "Honarable Adviser,Ministry of Environment,Forest and Climate Change and Ministry of Water Resources, Govenment of the people's Republic of Bangladesh",
    "categoryName": "Convocation"
  },
  {
    "id": "6d6fe8fc-e91f-4c42-85ec-4874ce10aaed",
    "image": "1747835732429-43085062.jpg",
    "imageTitle": "Campus Activation for Digital Bangladesh Mela",
    "categoryName": "Workshop"
  },
  {
    "id": "ddbe06f3-2a75-4482-ac93-2be4f8a0b84b",
    "image": "1747835859085-227422588.jpg",
    "imageTitle": "IUS Participates in AGREEN Foundation's Leadership development workshop",
    "categoryName": "Project Fair"
  },
  {
    "id": "6467f8d5-b1ee-4465-9b45-ddab318f37ea",
    "image": "1747836405833-598364689.jpg",
    "imageTitle": "She Innovates: Empowering Young Women in Tech Showcase Your Innovation and Inspire the Future of Engineering",
    "categoryName": "Project Fair"
  },
  {
    "id": "302b659b-12fa-44d1-af92-59d9d7283671",
    "image": "1747837089614-552055259.jpg",
    "imageTitle": "🤖 ROBO SOCCER ⚽ – Where Technology Meets the Thrill of the Game!",
    "categoryName": "Robbo Soccer"
  },
  {
    "id": "0a5c98c1-d181-4372-a25a-939b3607368d",
    "image": "1747837399249-593703644.jpg",
    "imageTitle": "⚽ Scholars Football Tournament 2025 – A Day to Remember! 🏆",
    "categoryName": "Sports"
  },
  {
    "id": "cffe04b8-d92a-43c8-a438-48f33ba49da8",
    "image": "1747837534978-820000193.jpg",
    "imageTitle": "1st Convocation of University of Scholars",
    "categoryName": "Convocation"
  },
  {
    "id": "4394e04c-dddb-43dc-8320-f5b257abd2e1",
    "image": "1747837932332-819857378.jpg",
    "imageTitle": "ThinkSpire 12: A Journey of Inspiration and Leadership",
    "categoryName": "Seminar"
  },
  {
    "id": "7434b5e2-3d2f-4ebb-b102-6ed3e037ccf9",
    "image": "1747838308443-823047980.jpg",
    "imageTitle": "Case Conquest 1.0: Celebrating Strategic Brilliance and Innovation A Thrilling Showcase of Business Acumen and Competitive Excellence",
    "categoryName": "Convocation"
  },
  {
    "id": "e1b0a998-41de-442f-8047-33027ca8f96b",
    "image": "1747839020402-953830581.jpg",
    "imageTitle": "Textile Engineering Shines at National Talent Hunt Students Achieve Top Honors in Season 9.0 Competition",
    "categoryName": "Project Fair"
  },
  {
    "id": "3ff739b4-3602-4181-baa1-68faf6324a48",
    "image": "1747839764243-112995033.png",
    "imageTitle": "Seminar on Unlocking Career & Academic Opportunities Through English Proficiency",
    "categoryName": "Seminar"
  },
  {
    "id": "919b8757-d589-48b7-9b29-e5f783a8632c",
    "image": "1747840333863-442428426.jpg",
    "imageTitle": "Convocation Speech Explanation – University of Scholars",
    "categoryName": "Convocation"
  },
  {
    "id": "16d8b1b0-5929-4b05-9acf-c9bddce2a069",
    "image": "1747840457734-894036034.jpg",
    "imageTitle": "CES 6th Intra University Programming Contest",
    "categoryName": "Programming Contest"
  },
  {
    "id": "1f524f87-22dc-4fd7-b2bf-17882f04e2f4",
    "image": "1747840894866-794236058.jpg",
    "imageTitle": "We’re thrilled to announce that ‘RoboMore Dynamic Sparks’, representing the University of Scholars, has emerged as the CHAMPION in the Line Follower Robot category at UIU CSE FEST 2025! 🚀",
    "categoryName": "Programming Contest"
  },
  {
    "id": "a335c4cd-8b53-46f3-b035-c7bd2d666bb2",
    "image": "1747841739083-276602743.jpg",
    "imageTitle": "University of Scholars Hosts Historic 1st Convocation Graduates Honored with Certificates and Medals for Academic Excellence",
    "categoryName": "Convocation"
  },
  {
    "id": "b02e52f6-a062-4dbb-bd09-75ec4f9030a6",
    "image": "1748028102291-338967535.jpg",
    "imageTitle": "Virtual Project Show 2025: Showcasing Innovation and Technical Excellence A Prestigious Platform for Future Tech Leaders at the University of Scholars",
    "categoryName": "Programming Contest"
  },
  {
    "id": "9e03410b-afb1-4fc5-93d8-495e2d9c340c",
    "image": "1747842918952-240801204.jpg",
    "imageTitle": "A Historic Milestone for the University of Scholars Celebrating Academic Excellence with Syeda Rizwana Hasan as Convocation President",
    "categoryName": "Convocation"
  },
  {
    "id": "f41d6881-5cfc-41c0-af6f-8d101206663e",
    "image": "1747843372906-711295157.jpg",
    "imageTitle": "Convocation 2025: A Moment of Triumph and New Beginnings Graduates Celebrate Success and Step Boldly Into the Future",
    "categoryName": "Convocation"
  },
  {
    "id": "c16eeed4-5f76-4877-99de-0d9d5466cec8",
    "image": "1747905892402-448670169.webp",
    "imageTitle": "Seminar image",
    "categoryName": "Seminar"
  },
  {
    "id": "34e7b51e-9ab7-4a0e-b4aa-1614b5210f90",
    "image": "1747941715971-489960060.jpg",
    "imageTitle": "\"University of Scholars Study Tour: Bridging Academic Learning with Real-World Experience\"",
    "categoryName": "Picnic or Study Tour"
  },
  {
    "id": "f85299b6-8e48-459b-b025-e8eb03f89955",
    "image": "1747942269158-382120417.jpg",
    "imageTitle": "\"2024 CSE Study Tour at the University of Scholars: A Pathway to Practical Excellence\"",
    "categoryName": "Picnic or Study Tour"
  },
  {
    "id": "dcb1ddde-9fa9-4b52-8650-20a8f110d378",
    "image": "1747943017156-492328188.jpg",
    "imageTitle": "A Journey of Learning Beyond the Classroom",
    "categoryName": "Picnic or Study Tour"
  },
  {
    "id": "e7130d22-4cec-451a-a08c-68f01cdb6f37",
    "image": "1747943420772-435452171.jpg",
    "imageTitle": "A Hands-On Learning Experience",
    "categoryName": "Workshop"
  },
  {
    "id": "ec705dd8-6495-4307-8aae-bdd9c2593825",
    "image": "1747943821669-869134407.jpg",
    "imageTitle": "🏭 Industrial Visit: Bridging Classroom Learning with Real-World Experience",
    "categoryName": "Industrial Visit"
  },
  {
    "id": "31f313bd-4a7b-45c3-9fbc-caf0f1948076",
    "image": "1747943953649-228054888.jpg",
    "imageTitle": "🏢 Example of an Industrial Visit: Visit to a Food Processing Plant",
    "categoryName": "Industrial Visit"
  },
  {
    "id": "4d9c3cf5-fcad-455d-9a22-072ac84ec2b0",
    "image": "1747944645169-907404149.jpeg",
    "imageTitle": "🏭 Industrial Visit to AGAMI CHASHI RANGPUR LTD (ACRL)",
    "categoryName": "Project Fair"
  },
  {
    "id": "a7bc632c-cec2-4c57-b353-98dc999d004e",
    "image": "1747945009864-866847324.png",
    "imageTitle": "🌍 Social Work: Serving Humanity, Building a Better Society",
    "categoryName": "Social events"
  },
  {
    "id": "906d6d6c-1961-475b-afb1-3d66ca1c85b3",
    "image": "1747945250295-14373373.jpeg",
    "imageTitle": "✨Social Work: An Essential Force for Social Change and Empowerment",
    "categoryName": "Social events"
  },
  {
    "id": "40cfbee9-4113-48e5-9ee1-66133c87cc27",
    "image": "1747945713501-299531246.jpg",
    "imageTitle": "🎉🍲 Food & Culture Festival 2025",
    "categoryName": "Festival"
  },
  {
    "id": "d672f7cb-ab8c-4daa-abb4-8e83aba89e34",
    "image": "1747946006992-465785498.avif",
    "imageTitle": "🤖⚽ Robosoccer Championship 2024",
    "categoryName": "Robbo Soccer"
  },
  {
    "id": "52b68019-59db-4d22-b539-4a6196586413",
    "image": "1747992148660-3556720.jpg",
    "imageTitle": "National Collegiate Programming Contest (NCPC): Igniting Innovation Through Competitive",
    "categoryName": "National Contest"
  },
  {
    "id": "034a77ea-b8e2-4798-a597-66f6319ad337",
    "image": "1747992985162-950960375.jpg",
    "imageTitle": "National Innovation and Entrepreneurship Contest (NIEC): Empowering Future Change-Makers",
    "categoryName": "National Contest"
  },
  {
    "id": "192c20fa-a1bd-4bec-a572-d9fe4057d0f6",
    "image": "1748016006791-621997874.webp",
    "imageTitle": "\"Robo Soccer at the University of Scholars: Fostering Innovation Through Robotics\"",
    "categoryName": "Robbo Soccer"
  },
  {
    "id": "789000d0-c360-4946-bbeb-bc670939d9be",
    "image": "1748016516501-597366648.avif",
    "imageTitle": "The youth steps forward for flood relief",
    "categoryName": "Social events"
  },
  {
    "id": "0db4e40f-d496-4b00-8ef8-3cd624661d93",
    "image": "1748027750341-359018082.jpg",
    "imageTitle": "🎓 Scholars Project Fair 2025",
    "categoryName": "Project Fair"
  },
  {
    "id": "31f8fdfb-f081-4b8c-8c33-667aa06b068d",
    "image": "1748028144191-322258524.jpg",
    "imageTitle": "How to Do a Science Fair Project – Science Project | NASA JPL Education",
    "categoryName": "Project Fair"
  },
  {
    "id": "5ebdcfbc-97d2-48b6-b6b9-473898c9bc53",
    "image": "1748028778963-365790809.jpeg",
    "imageTitle": "Programming Contest at 7th RUSC National Science Fiesta 2023",
    "categoryName": "Programming Contest"
  },
  {
    "id": "cde74f10-10e5-472e-9019-e1e0236acaed",
    "image": "1748029426544-343501189.webp",
    "imageTitle": "Dynamic Project Fair 2025: Innovation in Motion",
    "categoryName": "Project Fair"
  }
]